wadler_lindig/__init__.py
wadler_lindig/_ansi.py
wadler_lindig/_definitions.py
wadler_lindig/_wadler_lindig.py
wadler_lindig-0.1.6.dist-info/METADATA
wadler_lindig-0.1.6.dist-info/WHEEL
wadler_lindig-0.1.6.dist-info/licenses/LICENSE
wadler_lindig-0.1.6.dist-info/RECORD
